Metadata-Version: 2.1
Name: bgplot
Version: 0.0.11
Summary: A python library for basic geometry plotting that uses matplotlib as client
Author: Vistor
Project-URL: Homepage, https://github.com/vistormu/basic_geometry_plotter
Project-URL: Bug Tracker, https://github.com/vistormu/basic_geometry_plotter/issues
Classifier: Programming Language :: Python :: 3
Classifier: License :: OSI Approved :: MIT License
Classifier: Operating System :: OS Independent
Requires-Python: >=3.10
License-File: LICENSE
Requires-Dist: numpy
Requires-Dist: matplotlib (==3.6.3)
